{
  "scan_date": "2026-03-23",
  "scan_time": "07:29",
  "vix_value": 26.780000686645508,
  "dxy_value": 99.77200317382812,
  "us10y_value": 4.390999794006348,
  "market_regime": "RISK_OFF",
  "regime_report": "{\n  \"regime\": \"RISK_OFF\",\n  \"regime_description\": \"The VIX is elevated above 25, indicating heightened market fear and uncertainty. The US Dollar Index is at a relatively high level, and US Treasury yields are elevated, suggesting a preference for safety and a potential concern over inflation or growth outlook.\",\n  \"asset_biases\": {\n    \"equities\": \"bearish\",\n    \"commodities\": \"neutral\",\n    \"crypto\": \"bearish\",\n    \"safe_havens\": \"bullish\"\n  },\n  \"macro_risks\": [\n    \"Further escalation of geopolitical tensions could trigger a more severe flight to safety.\",\n    \"Unexpectedly strong inflation data could force central banks into more aggressive tightening, pressuring risk assets.\",\n    \"A significant corporate earnings miss could exacerbate equity market declines.\"\n  ],\n  \"key_levels\": {\n    \"vix_watch\": \"VIX above 30 would signal extreme fear and a potential capitulation event.\",\n    \"dxy_watch\": \"DXY breaking above 100.50 could indicate further dollar strength and pressure on global liquidity.\",\n    \"yield_watch\": \"US 10-Year Treasury Yields moving towards 4.50% would reinforce the risk-off sentiment and increase borrowing costs.\"\n  }\n}",
  "global_sentiment": "Förhöjd rädsla (VIX > 25). Svag dollar (DXY < 100). Neutral ränta (4.39%). Regim: RISK_OFF",
  "all_scores": [
    {
      "name": "DAX 40",
      "ticker": "^GDAXI",
      "score": 4.0,
      "direction": "BEAR",
      "confidence": 0.4,
      "summary": "",
      "lenses": {
        "trend": {
          "score": 2,
          "direction": "BEAR",
          "analysis": "The DAX 40 is in a bearish trend with mixed SMA alignment and price below the 50-week SMA, indicating a weak and unclear trend structure. The RSI is oversold, suggesting a potential bounce up.",
          "key_level": 22380.19
        },
        "reversal": {
          "score": 4,
          "direction": "BULL",
          "analysis": "The DAX 40 is showing signs of reversal safety with an oversold RSI of 28.1 and a potential bounce up, but the mixed SMA alignment and lack of clear trend indicate caution. The price is near the lower Bollinger Band, which could act as a support level.",
          "key_level": 22380.19
        },
        "momentum": {
          "score": 2,
          "direction": "BEAR",
          "analysis": "The MACD histogram is negative and the RSI is oversold, indicating a potential bounce but overall bearish momentum. The volume trend is neutral, not confirming a strong momentum shift.",
          "key_level": 22380.19
        },
        "volatility": {
          "score": 6,
          "direction": "BEAR",
          "analysis": "The Bollinger Band width is relatively high at 14.7%, and the ATR ratio is expanding, indicating increased volatility, but the price is already at the lower band, suggesting a potential bounce. The VIX correlation is aligned with the bearish market regime.",
          "key_level": 22507.79
        },
        "risk_reward": {
          "score": 6,
          "direction": "BEAR",
          "analysis": "The DAX 40 has a relatively high downside risk with a distance to nearest support of 3,729.97, and an upside potential of 1,095.82, resulting in a 1:3.4 R:R ratio, which is somewhat favorable for a bearish position.",
          "key_level": 22380.19
        }
      }
    },
    {
      "name": "OMXS30",
      "ticker": "^OMX",
      "score": 4.2,
      "direction": "BEAR",
      "confidence": 0.42,
      "summary": "",
      "lenses": {
        "trend": {
          "score": 3,
          "direction": "BEAR",
          "analysis": "The OMXS30 is in a bearish trend with mixed SMA alignment, but the price is above the 50-week SMA, indicating a slightly more stable trend structure. The RSI is oversold, suggesting a potential bounce up.",
          "key_level": 2864.69
        },
        "reversal": {
          "score": 5,
          "direction": "BULL",
          "analysis": "The OMXS30 is also oversold with an RSI of 28.3, and the price is below the lower Bollinger Band, which could indicate a potential bounce up. However, the mixed SMA alignment and lack of clear trend suggest caution.",
          "key_level": 2864.69
        },
        "momentum": {
          "score": 3,
          "direction": "BEAR",
          "analysis": "The MACD histogram is negative and the RSI is oversold, similar to the DAX, suggesting a potential bounce but bearish overall momentum. The volume trend is neutral, not adding to the momentum.",
          "key_level": 2864.69
        },
        "volatility": {
          "score": 5,
          "direction": "BEAR",
          "analysis": "The Bollinger Band width is relatively low at 13.5%, and the ATR ratio is expanding, indicating increased volatility, but the price is already below the lower band, suggesting a potential continuation of the downtrend. The VIX correlation is aligned with the bearish market regime.",
          "key_level": 3076.14
        },
        "risk_reward": {
          "score": 5,
          "direction": "BEAR",
          "analysis": "The OMXS30 has a downside risk of 209.03 and an upside potential of 211.45, resulting in a nearly 1:1 R:R ratio, which is not particularly favorable for a new position.",
          "key_level": 2864.69
        }
      }
    },
    {
      "name": "S&P 500",
      "ticker": "^GSPC",
      "score": 5.0,
      "direction": "BEAR",
      "confidence": 0.5,
      "summary": "",
      "lenses": {
        "trend": {
          "score": 4,
          "direction": "BEAR",
          "analysis": "The S&P 500 is in a bearish trend with mixed SMA alignment and price at the 50-week SMA, indicating a neutral and unclear trend structure. The RSI is oversold, suggesting a potential bounce up.",
          "key_level": 6506.48
        },
        "reversal": {
          "score": 6,
          "direction": "BULL",
          "analysis": "The S&P 500 is showing signs of reversal safety with an oversold RSI of 29.9 and a potential bounce up, and the price is near the lower Bollinger Band. The weekly SMA50 is also at the current price level, which could act as a support.",
          "key_level": 6506.48
        },
        "momentum": {
          "score": 4,
          "direction": "BEAR",
          "analysis": "The MACD histogram is negative and the RSI is oversold, indicating bearish momentum with a potential for a bounce. The volume trend is slightly above average, which could suggest a more significant move if momentum shifts.",
          "key_level": 6506.48
        },
        "volatility": {
          "score": 4,
          "direction": "BEAR",
          "analysis": "The Bollinger Band width is relatively low at 7.3%, and the ATR ratio is contracting, indicating decreased volatility, but the price is already below the lower band, suggesting a potential continuation of the downtrend. The VIX correlation is aligned with the bearish market regime.",
          "key_level": 6931.31
        },
        "risk_reward": {
          "score": 7,
          "direction": "BEAR",
          "analysis": "The S&P 500 has a downside risk of 733.17 and an upside potential of 454.83, resulting in a 1:1.6 R:R ratio, which is somewhat favorable for a bearish position given the oversold RSI and potential bounce.",
          "key_level": 6506.48
        }
      }
    },
    {
      "name": "Nasdaq",
      "ticker": "^IXIC",
      "score": 5.4,
      "direction": "BEAR",
      "confidence": 0.54,
      "summary": "",
      "lenses": {
        "trend": {
          "score": 5,
          "direction": "BEAR",
          "analysis": "The Nasdaq is in a bearish trend with mixed SMA alignment and price at the 50-week SMA, indicating a neutral and unclear trend structure. The RSI is approaching oversold, suggesting a potential bounce up.",
          "key_level": 21647.61
        },
        "reversal": {
          "score": 8,
          "direction": "NEUTRAL",
          "analysis": "The Nasdaq is approaching oversold levels with an RSI of 33.6, but the price is still below the lower Bollinger Band. The weekly SMA50 is also at the current price level, which could act as a support, but the lack of clear trend and mixed SMA alignment suggest caution.",
          "key_level": 21647.61
        },
        "momentum": {
          "score": 5,
          "direction": "BEAR",
          "analysis": "The MACD histogram is negative, and the RSI is approaching oversold levels, suggesting bearish momentum. The volume trend is slightly above average, similar to the S&P 500, which might indicate a more substantial move if the trend reverses.",
          "key_level": 21647.61
        },
        "volatility": {
          "score": 5,
          "direction": "BEAR",
          "analysis": "The Bollinger Band width is relatively low at 6.4%, and the ATR ratio is contracting, indicating decreased volatility, but the price is already below the lower band, suggesting a potential continuation of the downtrend. The VIX correlation is aligned with the bearish market regime.",
          "key_level": 24004.13
        },
        "risk_reward": {
          "score": 4,
          "direction": "BEAR",
          "analysis": "The Nasdaq has a downside risk of 2,815.70 and an upside potential of 356.49, resulting in a 1:7.9 R:R ratio, which is not particularly favorable for a new bearish position.",
          "key_level": 21647.61
        }
      }
    },
    {
      "name": "FTSE 100",
      "ticker": "^FTSE",
      "score": 4.0,
      "direction": "BEAR",
      "confidence": 0.4,
      "summary": "",
      "lenses": {
        "trend": {
          "score": 4,
          "direction": "BEAR",
          "analysis": "The primary trend is bearish with a mixed SMA alignment, and the price is above the 50-week SMA, indicating a potential for further decline.",
          "key_level": 9942.33
        },
        "reversal": {
          "score": 4,
          "direction": "BULL",
          "analysis": "The RSI is approaching oversold levels at 32.4, indicating a potential reversal, and the price is below the lower Bollinger Band, suggesting a possible bounce. The lack of a clear trend alignment and the mixed SMA bias add to the reversal risk.",
          "key_level": 9930.1
        },
        "momentum": {
          "score": 2,
          "direction": "BEAR",
          "analysis": "The MACD histogram is negative and the RSI is approaching oversold levels, indicating weak momentum. The volume trend is also flat, confirming the bearish momentum.",
          "key_level": 9930.1
        },
        "volatility": {
          "score": 4,
          "direction": "BEAR",
          "analysis": "The Bollinger Band width is relatively high at 10.7%, and the ATR ratio is 1.5x, indicating ongoing volatility, but no clear squeeze or breakout setup. The RSI is approaching oversold, which could lead to a bounce, but the overall trend remains bearish.",
          "key_level": 9930.1
        },
        "risk_reward": {
          "score": 6,
          "direction": "BEAR",
          "analysis": "The FTSE 100 is approaching oversold levels with an RSI of 32.4, but the bearish SMA bias and mixed alignment suggest caution, with a nearby support at 9,423.90 and resistance at 9,930.10.",
          "key_level": 9423.9
        }
      }
    },
    {
      "name": "Nikkei 225",
      "ticker": "^N225",
      "score": 4.6,
      "direction": "BEAR",
      "confidence": 0.46,
      "summary": "",
      "lenses": {
        "trend": {
          "score": 5,
          "direction": "BEAR",
          "analysis": "The primary trend is bearish with a mixed SMA alignment, and the price is above the 50-week SMA, suggesting a potential for further downside.",
          "key_level": 51515.49
        },
        "reversal": {
          "score": 5,
          "direction": "BULL",
          "analysis": "The RSI is approaching oversold levels at 37.3, and the MACD histogram is negative, but the price is still within the Bollinger Band, reducing the reversal risk. The mixed SMA bias and lack of clear trend alignment contribute to the moderate reversal risk.",
          "key_level": 52335.3
        },
        "momentum": {
          "score": 3,
          "direction": "BEAR",
          "analysis": "The MACD histogram is negative and the RSI is approaching oversold levels, indicating weak momentum. However, the asset is still within the Bollinger Band, suggesting some potential for a bounce.",
          "key_level": 52335.3
        },
        "volatility": {
          "score": 5,
          "direction": "BEAR",
          "analysis": "The Bollinger Band width is relatively high at 16.4%, and the ATR ratio is 1.4x, indicating ongoing volatility, but the bands are not squeezing, and the price is trading within the band. The RSI is approaching oversold, which could lead to a bounce, but the overall trend remains bearish.",
          "key_level": 52367.87
        },
        "risk_reward": {
          "score": 5,
          "direction": "BEAR",
          "analysis": "The Nikkei 225 is also approaching oversold levels with an RSI of 37.3, but the bearish SMA bias and mixed alignment indicate a potential for further decline, with a nearby support at 48,235.30 and resistance at 52,636.87.",
          "key_level": 48235.3
        }
      }
    },
    {
      "name": "Hang Seng",
      "ticker": "^HSI",
      "score": 2.8,
      "direction": "BEAR",
      "confidence": 0.28,
      "summary": "",
      "lenses": {
        "trend": {
          "score": 3,
          "direction": "BEAR",
          "analysis": "The primary trend is bearish with a mixed SMA alignment, and the price is below the 50-week SMA, indicating a strong downtrend.",
          "key_level": 24246.72
        },
        "reversal": {
          "score": 3,
          "direction": "BULL",
          "analysis": "The RSI is approaching oversold levels at 31.4, and the MACD has a bearish cross, indicating a potential reversal. The price is below the lower Bollinger Band, and the lack of clear trend alignment increases the reversal risk.",
          "key_level": 24157.31
        },
        "momentum": {
          "score": 1,
          "direction": "BEAR",
          "analysis": "The MACD histogram is negative, the RSI is approaching oversold levels, and the asset has broken below the lower Bollinger Band, indicating very weak momentum. The bearish cross on the MACD also confirms the bearish trend.",
          "key_level": 24157.31
        },
        "volatility": {
          "score": 3,
          "direction": "BEAR",
          "analysis": "The Bollinger Band width is relatively low at 9.5%, and the ATR ratio is 1.1x, indicating consolidating volatility, but the price is trading below the lower band, which could lead to further downside. The RSI is approaching oversold, which could lead to a bounce, but the overall trend remains bearish.",
          "key_level": 24174.39
        },
        "risk_reward": {
          "score": 4,
          "direction": "BEAR",
          "analysis": "The Hang Seng index has a bearish cross in the MACD and is below the lower Bollinger Band, suggesting a higher downside risk, with a nearby support at 19,157.31 and resistance at 24,874.39.",
          "key_level": 19157.31
        }
      }
    },
    {
      "name": "Guld",
      "ticker": "GC=F",
      "score": 4.8,
      "direction": "BULL",
      "confidence": 0.48,
      "summary": "",
      "lenses": {
        "trend": {
          "score": 2,
          "direction": "BEAR",
          "analysis": "The primary trend is bearish with a mixed SMA alignment, and the price is above the 50-week SMA, but the RSI is oversold, suggesting a potential bounce.",
          "key_level": 4148.4
        },
        "reversal": {
          "score": 2,
          "direction": "BULL",
          "analysis": "The RSI is oversold at 23.3, indicating a high potential for reversal, and the price is below the lower Bollinger Band, suggesting a possible bounce. The high volume and mixed SMA bias contribute to the high reversal risk.",
          "key_level": 3263.9
        },
        "momentum": {
          "score": 4,
          "direction": "NEUTRAL",
          "analysis": "The RSI is oversold, which could indicate a potential bounce, and the volume trend is expanding, which could be a sign of a reversal. However, the MACD histogram is still negative, keeping the momentum score low.",
          "key_level": 3263.9
        },
        "volatility": {
          "score": 8,
          "direction": "BULL",
          "analysis": "The Bollinger Band width is relatively high at 26.8%, and the ATR ratio is 0.8x, indicating a potential breakout setup, and the RSI is oversold, which could lead to a bounce. The price is trading below the lower band, but the overall volatility setup is favorable for a potential upside move.",
          "key_level": 4358.0
        },
        "risk_reward": {
          "score": 8,
          "direction": "BULL",
          "analysis": "Gold is oversold with an RSI of 23.3 and has a high potential for a bounce, with a nearby support at 3,263.90 and resistance at 4,358.00, making it a more attractive risk-reward opportunity.",
          "key_level": 3263.9
        }
      }
    },
    {
      "name": "Silver",
      "ticker": "SI=F",
      "score": 3.3,
      "direction": "NEUTRAL",
      "confidence": 0.33,
      "summary": "",
      "lenses": {
        "reversal": {
          "score": 4,
          "direction": "BULL",
          "analysis": "The RSI is approaching oversold levels and the price is below the lower Bollinger Band, indicating potential reversal safety, but the SMA bias is bearish and the trend alignment is mixed.",
          "key_level": 67.0
        },
        "momentum": {
          "score": 2,
          "direction": "BEAR",
          "analysis": "The MACD histogram is negative and the RSI is approaching oversold levels, indicating weak momentum. The volume trend is also contracting with price, further confirming the bearish momentum.",
          "key_level": 62.15
        },
        "volatility": {
          "score": 4,
          "direction": "BEAR",
          "analysis": "The Bollinger Band width is relatively wide, and the ATR trend is not showing a clear expansion, indicating a lack of volatility setup for a breakout. The RSI is approaching oversold, which could lead to a bounce, but the overall setup is not favorable.",
          "key_level": 67.0
        }
      }
    },
    {
      "name": "Olja (WTI)",
      "ticker": "CL=F",
      "score": 8.0,
      "direction": "NEUTRAL",
      "confidence": 0.8,
      "summary": "",
      "lenses": {
        "reversal": {
          "score": 8,
          "direction": "BEAR",
          "analysis": "The RSI is overbought and the price is in a strong uptrend, but there are no clear reversal signals, making it relatively safe to trade, but caution is advised due to the overbought conditions.",
          "key_level": 110.84
        },
        "momentum": {
          "score": 8,
          "direction": "BULL",
          "analysis": "The MACD histogram is positive and the RSI is overbought, indicating strong momentum. However, the volume trend is contracting with price, which may indicate a potential pullback.",
          "key_level": 100.73
        },
        "volatility": {
          "score": 8,
          "direction": "BULL",
          "analysis": "The asset is overbought, but the Bollinger Band width is relatively wide, and the ATR trend is expanding, indicating a strong uptrend. A potential pullback could be a buying opportunity, given the strong bullish alignment of the SMAs.",
          "key_level": 110.84
        }
      }
    },
    {
      "name": "Naturgas",
      "ticker": "NG=F",
      "score": 4.0,
      "direction": "NEUTRAL",
      "confidence": 0.4,
      "summary": "",
      "lenses": {
        "reversal": {
          "score": 6,
          "direction": "NEUTRAL",
          "analysis": "The RSI is neutral and the SMA bias is bearish, but the trend alignment is mixed, and there are no clear reversal signals, making it a neutral trade.",
          "key_level": 3.27
        },
        "momentum": {
          "score": 4,
          "direction": "NEUTRAL",
          "analysis": "The MACD histogram is neutral and the RSI is in the neutral zone, indicating a lack of clear momentum. The volume trend is also flat, confirming the neutral momentum.",
          "key_level": 3.12
        },
        "volatility": {
          "score": 2,
          "direction": "NEUTRAL",
          "analysis": "The Bollinger Band width is very narrow, indicating a potential breakout, but the ATR trend is contracting, and the RSI is neutral, suggesting a lack of clear direction. The overall setup is not favorable for a significant move.",
          "key_level": 3.27
        }
      }
    },
    {
      "name": "Platina",
      "ticker": "PL=F",
      "score": 3.3,
      "direction": "NEUTRAL",
      "confidence": 0.33,
      "summary": "",
      "lenses": {
        "reversal": {
          "score": 3,
          "direction": "BULL",
          "analysis": "The RSI is approaching oversold levels and the price is below the lower Bollinger Band, indicating potential reversal safety, and the weekly SMA50 is above the price, making it a potential bullish reversal candidate.",
          "key_level": 1854.47
        },
        "momentum": {
          "score": 1,
          "direction": "BEAR",
          "analysis": "The MACD histogram is negative and the RSI is approaching oversold levels, indicating very weak momentum. The volume trend is expanding with price, but in a bearish direction, further confirming the weak momentum.",
          "key_level": 1769.4
        },
        "volatility": {
          "score": 6,
          "direction": "BEAR",
          "analysis": "The Bollinger Band width is relatively wide, and the ATR trend is not showing a clear expansion, but the RSI is approaching oversold, which could lead to a bounce. However, the overall setup is still bearish, given the bearish SMA alignment.",
          "key_level": 1854.47
        }
      }
    },
    {
      "name": "Koppar",
      "ticker": "HG=F",
      "score": 4.8,
      "direction": "BEAR",
      "confidence": 0.48,
      "summary": "",
      "lenses": {
        "trend": {
          "score": 4,
          "direction": "BEAR",
          "analysis": "The primary trend is bearish with a mixed SMA alignment, and the price is below the 50-day SMA but above the 200-day SMA, indicating a potential reversal. The RSI is approaching oversold levels, which could lead to a bounce.",
          "key_level": 5.35
        },
        "reversal": {
          "score": 4,
          "direction": "BULL",
          "analysis": "The RSI is approaching oversold levels at 31.5, indicating a potential reversal, and the price is below the lower Bollinger Band, suggesting exhaustion. The recent price action has not formed a double top or bottom, but the RSI divergence and low RSI value increase the reversal safety score.",
          "key_level": 4.32
        },
        "momentum": {
          "score": 2,
          "direction": "BEAR",
          "analysis": "The MACD histogram is negative and the RSI is approaching oversold levels, indicating weak momentum, while the volume trend is not confirming a bullish reversal.",
          "key_level": 5.35
        },
        "volatility": {
          "score": 6,
          "direction": "BEAR",
          "analysis": "The Bollinger Band width is relatively high at 15.5%, and the ATR is expanding, indicating a potential continuation of the downtrend. The RSI is approaching oversold levels, which could lead to a bounce, but the overall volatility setup suggests a bearish bias.",
          "key_level": 5.35
        },
        "risk_reward": {
          "score": 8,
          "direction": "BULL",
          "analysis": "The asset is approaching oversold levels with an RSI of 31.5, and the distance to the nearest support is relatively small, while the distance to the nearest resistance is larger, indicating a favorable risk-reward ratio. The current price is below the lower Bollinger Band, which could lead to a bounce.",
          "key_level": 4.32
        }
      }
    },
    {
      "name": "Bitcoin",
      "ticker": "BTC-USD",
      "score": 4.0,
      "direction": "BEAR",
      "confidence": 0.4,
      "summary": "",
      "lenses": {
        "trend": {
          "score": 3,
          "direction": "BEAR",
          "analysis": "The primary trend is bearish with a mixed SMA alignment, and the price is below the 50-day and 200-day SMAs, indicating a strong downtrend. The MACD has a bearish cross, confirming the bearish trend.",
          "key_level": 65000.0
        },
        "reversal": {
          "score": 6,
          "direction": "NEUTRAL",
          "analysis": "The RSI is in the neutral zone at 43.7, and the MACD has formed a bearish cross, but there are no clear signs of exhaustion or RSI divergence. The price is within the Bollinger Band, and the recent volume is below average, reducing the likelihood of a reversal.",
          "key_level": 60074.2
        },
        "momentum": {
          "score": 3,
          "direction": "BEAR",
          "analysis": "The MACD histogram is negative with a bearish crossover, and the RSI is in the neutral zone, indicating a lack of strong momentum, while the volume trend is contracting.",
          "key_level": 65895.21
        },
        "volatility": {
          "score": 4,
          "direction": "BEAR",
          "analysis": "The Bollinger Band width is relatively narrow at 13.4%, but the ATR is contracting, indicating a consolidation phase. The MACD bearish cross and the RSI in the neutral zone suggest a bearish bias, but the volatility setup is not ideal for a breakout.",
          "key_level": 65000.0
        },
        "risk_reward": {
          "score": 4,
          "direction": "BEAR",
          "analysis": "The asset has a bearish cross in the MACD and is currently in a neutral RSI zone, with a relatively large distance to the nearest support and a small distance to the nearest resistance, indicating a poor risk-reward ratio. The overall trend is bearish, with a SMA bias and a bearish cross.",
          "key_level": 60074.2
        }
      }
    },
    {
      "name": "Ethereum",
      "ticker": "ETH-USD",
      "score": 4.4,
      "direction": "BEAR",
      "confidence": 0.44,
      "summary": "",
      "lenses": {
        "trend": {
          "score": 3,
          "direction": "BEAR",
          "analysis": "The primary trend is bearish with a mixed SMA alignment, and the price is below the 50-day and 200-day SMAs, indicating a strong downtrend. The MACD has a bearish cross, confirming the bearish trend, and the RSI is in the neutral zone.",
          "key_level": 1800.0
        },
        "reversal": {
          "score": 5,
          "direction": "NEUTRAL",
          "analysis": "The RSI is in the neutral zone at 45.1, and the MACD has formed a bearish cross, but there are no clear signs of exhaustion or RSI divergence. The price is within the Bollinger Band, and the recent volume is below average, reducing the likelihood of a reversal, but the wider Bollinger Band width increases the potential for a move.",
          "key_level": 1754.78
        },
        "momentum": {
          "score": 4,
          "direction": "BEAR",
          "analysis": "The MACD histogram is negative with a bearish crossover, and the RSI is in the neutral zone, indicating a lack of strong momentum, while the volume trend is contracting, but the price is holding above the lower Bollinger Band.",
          "key_level": 1883.15
        },
        "volatility": {
          "score": 5,
          "direction": "BEAR",
          "analysis": "The Bollinger Band width is relatively wide at 20.9%, and the ATR is stable, indicating a potential breakout. However, the MACD bearish cross and the RSI in the neutral zone suggest a bearish bias, and the volatility setup is not strongly supportive of a bullish move.",
          "key_level": 1800.0
        },
        "risk_reward": {
          "score": 5,
          "direction": "BEAR",
          "analysis": "The asset has a bearish cross in the MACD and is currently in a neutral RSI zone, with a relatively large distance to the nearest support and a small distance to the nearest resistance, indicating a mediocre risk-reward ratio. The overall trend is bearish, with a SMA bias and a bearish cross.",
          "key_level": 1754.78
        }
      }
    },
    {
      "name": "Solana",
      "ticker": "SOL-USD",
      "score": 4.0,
      "direction": "BEAR",
      "confidence": 0.4,
      "summary": "",
      "lenses": {
        "trend": {
          "score": 2,
          "direction": "BEAR",
          "analysis": "The primary trend is bearish with a mixed SMA alignment, and the price is below the 50-day and 200-day SMAs, indicating a strong downtrend. The MACD has a bearish cross, confirming the bearish trend, and the RSI is in the neutral zone, indicating a potential continuation of the downtrend.",
          "key_level": 70.0
        },
        "reversal": {
          "score": 6,
          "direction": "NEUTRAL",
          "analysis": "The RSI is in the neutral zone at 44.6, and the MACD has formed a bearish cross, but there are no clear signs of exhaustion or RSI divergence. The price is within the Bollinger Band, and the recent volume is below average, reducing the likelihood of a reversal, and the narrow Bollinger Band width reduces the potential for a large move.",
          "key_level": 68.69
        },
        "momentum": {
          "score": 3,
          "direction": "BEAR",
          "analysis": "The MACD histogram is negative with a bearish crossover, and the RSI is in the neutral zone, indicating a lack of strong momentum, while the volume trend is contracting, and the price is trading within the Bollinger Bands.",
          "key_level": 80.78
        },
        "volatility": {
          "score": 3,
          "direction": "BEAR",
          "analysis": "The Bollinger Band width is relatively narrow at 17.0%, and the ATR is contracting, indicating a consolidation phase. The MACD bearish cross and the RSI in the neutral zone suggest a bearish bias, and the volatility setup is not ideal for a breakout.",
          "key_level": 70.0
        },
        "risk_reward": {
          "score": 6,
          "direction": "BEAR",
          "analysis": "The asset has a bearish cross in the MACD and is currently in a neutral RSI zone, with a relatively small distance to the nearest support and a large distance to the nearest resistance, indicating a somewhat favorable risk-reward ratio. However, the overall trend is bearish, with a SMA bias and a bearish cross.",
          "key_level": 68.69
        }
      }
    },
    {
      "name": "XRP",
      "ticker": "XRP-USD",
      "score": 4.0,
      "direction": "BEAR",
      "confidence": 0.4,
      "summary": "",
      "lenses": {
        "trend": {
          "score": 8,
          "direction": "BEAR",
          "analysis": "The asset's SMA alignment is bearish with a strong downtrend, and the price is below the 50-week SMA, indicating a clear bearish trend structure. The bearish cross in the MACD and the price being below the SMA20, SMA50, and SMA200 further support this analysis.",
          "key_level": 1.41
        },
        "reversal": {
          "score": 4,
          "direction": "BULL",
          "analysis": "The RSI is in the neutral zone and the price is making new lows, but the RSI is not making new lows, indicating a potential bullish divergence. The bearish cross in the MACD and the strong downtrend suggest a high reversal risk.",
          "key_level": 1.27
        },
        "momentum": {
          "score": 2,
          "direction": "BEAR",
          "analysis": "The MACD histogram is bearish with a downward direction, and the RSI is neutral but has room to fall, indicating weak momentum to the downside. Volume is also contracting with price, confirming the bearish momentum.",
          "key_level": 1.27
        },
        "volatility": {
          "score": 4,
          "direction": "BEAR",
          "analysis": "The Bollinger Band width is relatively wide at 15.5%, and the ATR trend is contracting, indicating a consolidation phase. The VIX correlation suggests that macro volatility is not aligned with XRP's current price action, contributing to a mediocre volatility setup.",
          "key_level": 1.27
        },
        "risk_reward": {
          "score": 2,
          "direction": "BEAR",
          "analysis": "The strong downtrend and bearish cross in the MACD indicate a high likelihood of further price decline, with the nearest support at 1.27, while the nearest resistance is at 2.41, resulting in a poor risk-reward ratio.",
          "key_level": 1.27
        }
      }
    }
  ],
  "top5": [
    {
      "asset": {
        "ticker": "CL=F",
        "display_name": "Olja (WTI)",
        "news_keywords": [
          "oil price",
          "crude oil",
          "WTI",
          "OPEC"
        ],
        "asset_type": "commodity",
        "category": "Råvaror"
      },
      "tech": {
        "current_price": 100.73,
        "rsi_value": 72.79,
        "sma_20": 84.84,
        "sma_50": 71.56,
        "sma_200": 64.84,
        "sma_50w": 64.67,
        "atr_value": 10.66,
        "price_vs_sma": "above",
        "price_vs_weekly_sma": "above",
        "sma_alignment": "bullish_stack",
        "sma_bias": "bullish",
        "rsi_trend_2d": 3.33,
        "atr_ratio": 2.09,
        "volume_ratio": 0.16,
        "vix_value": 26.78,
        "vix_level": "elevated",
        "near_resistance": false,
        "near_support": false,
        "supports": [
          72.48,
          65.7,
          55.48
        ],
        "resistances": [],
        "macd_value": 8.6695,
        "macd_signal": 7.7785,
        "macd_histogram": 0.8909,
        "macd_cross": "none",
        "bb_upper": 110.84,
        "bb_lower": 58.84,
        "bb_middle": 84.84,
        "bb_position": "in_band",
        "bb_width": 51.62
      },
      "stage2": {
        "lenses": {
          "reversal": {
            "score": 8,
            "direction": "BEAR",
            "analysis": "The RSI is overbought and the price is in a strong uptrend, but there are no clear reversal signals, making it relatively safe to trade, but caution is advised due to the overbought conditions.",
            "key_level": 110.84
          },
          "momentum": {
            "score": 8,
            "direction": "BULL",
            "analysis": "The MACD histogram is positive and the RSI is overbought, indicating strong momentum. However, the volume trend is contracting with price, which may indicate a potential pullback.",
            "key_level": 100.73
          },
          "volatility": {
            "score": 8,
            "direction": "BULL",
            "analysis": "The asset is overbought, but the Bollinger Band width is relatively wide, and the ATR trend is expanding, indicating a strong uptrend. A potential pullback could be a buying opportunity, given the strong bullish alignment of the SMAs.",
            "key_level": 110.84
          }
        },
        "composite_score": 8.0,
        "consensus_direction": "NEUTRAL",
        "confidence": 0.8
      },
      "stage5": {
        "A": {
          "analogs": [
            {
              "period": "Mid-2022 Rate Hike Cycle",
              "description": "WTI was experiencing upward price pressure amidst a hawkish monetary policy environment, with RSI indicating overbought conditions and a bullish SMA bias.",
              "outcome": "WTI experienced a significant pullback, dropping approximately 15-20% within 20 trading days as inflation concerns and recession fears intensified, leading to reduced demand expectations.",
              "relevance_score": 7
            },
            {
              "period": "Early 2022 Ukraine Invasion Escalation",
              "description": "Similar to the current setup, WTI was trading at elevated levels with a strong bullish technical bias (SMA, RSI) driven by geopolitical supply shock concerns, despite a risk-off market regime.",
              "outcome": "WTI initially surged further, but then experienced volatility and a subsequent decline of 10-15% within 10-15 trading days as the initial shock subsided and concerns about global economic slowdown grew.",
              "relevance_score": 6
            },
            {
              "period": "Late 2007 Pre-Financial Crisis Peak",
              "description": "WTI was trading at high levels with strong bullish technical indicators, while underlying macro conditions were beginning to show signs of stress (though not yet a full risk-off regime).",
              "outcome": "WTI continued to climb for a short period, but then entered a sharp decline of over 30% within 20 trading days as the financial crisis unfolded and demand collapsed.",
              "relevance_score": 5
            }
          ],
          "historical_verdict": "BEARISH",
          "confidence_from_history": 0.6,
          "key_lesson": "Elevated prices and strong bullish technicals in a risk-off environment often precede sharp corrections as macro headwinds eventually dominate."
        },
        "B": {
          "dxy_correlation": "negative",
          "dxy_verdict": "contradicts",
          "yield_impact": "undermining",
          "currency_adjusted": false,
          "real_move_confidence": 0.3,
          "cross_asset_confirmation": "weak",
          "inter_market_verdict": "DIVERGENT",
          "analysis": "WTI typically has a negative correlation with the DXY, meaning a rising dollar should pressure oil prices. The current DXY move is rising, contradicting the current WTI price action. Rising US 10Y yields also tend to undermine oil prices by increasing borrowing costs and potentially signaling slower economic growth, which is also a headwind. While some energy stocks might show resilience, the broader cross-asset picture, particularly the dollar and yields, suggests the current oil move is not well-supported by inter-market forces."
        },
        "C": {
          "supply_pressure": "balanced",
          "demand_trend": "falling",
          "geopolitical_risk": "HIGH",
          "geopolitical_factors": [
            "Ongoing geopolitical tensions can lead to supply disruptions or influence trade routes, impacting WTI prices.",
            "Sanctions and trade disputes can alter global oil flows and demand patterns."
          ],
          "seasonal_bias": "neutral",
          "fundamental_verdict": "BEARISH",
          "confidence": 0.7,
          "key_driver": "A bearish outlook for Brent in 2026, as indicated by recent news, suggests a potential oversupply scenario or weakening demand in the medium term, which could spill over to WTI."
        },
        "D": null
      },
      "stage6": null,
      "stage7": {
        "hallucinations_found": [],
        "logical_errors": [
          "The original AI analysis has a composite score of 8.0/10 with a direction of NEUTRAL, but all available verdicts (Historical Analogs, Fundamental) are BEARISH, indicating a potential contradiction."
        ],
        "missing_risks": [
          "The analysis does not consider the high RSI value of 72.8, which may indicate overbought conditions and potential for a price correction."
        ],
        "overconfidence": true,
        "adjusted_confidence": 0.6,
        "validation_passed": false,
        "final_verdict": "REDUCE_CONFIDENCE",
        "auditor_notes": "The analysis lacks consistency between the composite score and the verdicts from different stages. The high RSI value and low volume are not adequately addressed, suggesting potential overconfidence in the neutral direction. Further review is necessary to reconcile these discrepancies."
      },
      "synthesis": {
        "verdict": "NO_TRADE",
        "final_confidence": 0.4,
        "chain_of_thought": "Analysen av olja (WTI) visar en komplex bild med både bulliska och beariska signaler. Den kvantitativa analysen ger ett kompositbetyg på 8,0/10 med en neutral riktning, men med en överköpt RSI och en stark uppåtgående trend. Samtidigt visar den djupgående forskningen en bearisk utblick med en konfidens på 60% baserat på historiska analogier, och fundamentala faktorer som tyder på en potential överskotts- eller efterfrågesituation i medeltermen. Intermarknadsanalysen visar också en divergens mellan WTI och DXY, vilket kan tyda på en korrektion. Korsvalideringen resulterar i en reducerad konfidens på 60% på grund av inkonsekvenser i analysen. Med tanke på den låga konfidensen och de motstridiga signalerna, är det bäst att avstå från handel för tillfället.",
        "entry_price": 0.0,
        "stop_loss": 0.0,
        "take_profit": 0.0,
        "risk_reward": "Ingen",
        "key_catalyst": "Inga tydliga katalysatorer för en tydlig riktning",
        "biggest_risk": "Den största risken är att marknaden korrektar nedåt på grund av de överköpta signalerna och de fundamentala faktorerna",
        "time_horizon": "Ingen",
        "exit_strategy": "Ingen, eftersom ingen position tas"
      },
      "headlines": [
        {
          "headline": "Crude Oil Forecasts & Analysis",
          "source": "www.fxempire.com",
          "datetime": "2026-03-23",
          "url": "https://www.fxempire.com/forecasts/wti-crude-oil",
          "summary": "Discover today's Crude Oil price forecast with expert analysis, Crude Oil price predictions, in-depth Crude Oil technical analysis, and the latest economic"
        },
        {
          "headline": "Crude Oil - Price - Chart - Historical Data - News",
          "source": "tradingeconomics.com",
          "datetime": "2026-03-23",
          "url": "https://tradingeconomics.com/commodity/crude-oil",
          "summary": "Crude Oil rose to 99.10 USD/Bbl on March 23, 2026, up 0.89% from the previous day. Over the past month, Crude Oil's price has risen 51.00%, and is up 43.40%"
        },
        {
          "headline": "Short-Term Energy Outlook",
          "source": "www.eia.gov",
          "datetime": "2026-03-23",
          "url": "https://www.eia.gov/outlooks/steo/",
          "summary": "We forecast the Brent crude oil price will remain above $95/b over the next two months, before falling below $80/b in the third quarter of 2026 and around $70/b"
        },
        {
          "headline": "Crude Oil Prices Today | OilPrice.com",
          "source": "oilprice.com",
          "datetime": "2026-03-23",
          "url": "https://oilprice.com/",
          "summary": "Oil is heading for a fifth straight weekly gain, with Brent near $109, as the Strait of Hormuz remains shut for a third week, keeping supply tight despite"
        },
        {
          "headline": "Crude Oil Prices Today and Oil Market News",
          "source": "www.cnbc.com",
          "datetime": "2026-03-23",
          "url": "https://www.cnbc.com/oil/",
          "summary": "Follow today's crude oil price moves and key news stories driving oil price actions, as well as developments in the broader energy sector."
        },
        {
          "headline": "Oil News Today | OilPrice.com",
          "source": "oilprice.com",
          "datetime": "2026-03-23",
          "url": "https://oilprice.com/Latest-Energy-News/World-News/",
          "summary": "Oil Prices Ease As US Pulls Out All Stops To Secure Supply · U.S. Bets on Natural Gas to Power 10 GW AI Buildout in Ohio · Asian Refiners Pay Record Premiums for"
        },
        {
          "headline": "Oil price forecast: A bearish outlook for Brent in 2026",
          "source": "www.jpmorgan.com",
          "datetime": "2026-03-23",
          "url": "https://www.jpmorgan.com/insights/global-research/commodities/oil-prices",
          "summary": "Despite a recent spike in oil prices, J.P. Morgan Global Research expects to see Brent crude averaging around $60/bbl in 2026. This bearish"
        },
        {
          "headline": "Crude Oil Futures Price Today (WTI)",
          "source": "www.investing.com",
          "datetime": "2026-03-23",
          "url": "https://www.investing.com/commodities/crude-oil",
          "summary": "The current price of Crude Oil WTI futures is 99.26, with a previous close of 98.23. What Is the Daily Trading Range for Crude Oil WTI Futures?"
        },
        {
          "headline": "Crude Oil Price, Oil, Energy, Petroleum, Oil Price, WTI & Brent ...",
          "source": "www.oil-price.net",
          "datetime": "2026-03-23",
          "url": "https://www.oil-price.net/",
          "summary": "Commodities. Crude Oil, 90.88, +0.01%. Natural Gas, 3.17, +3.19%. Gasoline, 3.13, +0.91%. Heating Oil, 4.34, +3.32%. Gold, 4600.70, -6.29%."
        },
        {
          "headline": "Energy",
          "source": "www.bloomberg.com",
          "datetime": "2026-03-23",
          "url": "https://www.bloomberg.com/energy",
          "summary": "Get updated data about energy and oil prices. Find natural gas, emissions, and crude oil price changes."
        }
      ],
      "final_verdict": "NO_TRADE",
      "final_confidence": 0.4,
      "trading_plan": null
    },
    {
      "asset": {
        "ticker": "^IXIC",
        "display_name": "Nasdaq",
        "news_keywords": [
          "Nasdaq",
          "tech stocks",
          "US technology"
        ],
        "asset_type": "index",
        "category": "Index"
      },
      "tech": {
        "current_price": 21647.61,
        "rsi_value": 33.62,
        "sma_20": 22533.51,
        "sma_50": 22961.95,
        "sma_200": 22248.95,
        "sma_50w": 21506.28,
        "atr_value": 412.71,
        "price_vs_sma": "below",
        "price_vs_weekly_sma": "at",
        "sma_alignment": "mixed",
        "sma_bias": "bearish",
        "rsi_trend_2d": -6.68,
        "atr_ratio": 1.01,
        "volume_ratio": 1.15,
        "vix_value": 26.78,
        "vix_level": "elevated",
        "near_resistance": false,
        "near_support": false,
        "supports": [
          18831.91,
          15708.54,
          15222.78
        ],
        "resistances": [
          24004.13
        ],
        "macd_value": -255.6565,
        "macd_signal": -192.7981,
        "macd_histogram": -62.8584,
        "macd_cross": "none",
        "bb_upper": 23229.4,
        "bb_lower": 21837.62,
        "bb_middle": 22533.51,
        "bb_position": "below_lower",
        "bb_width": 6.43
      },
      "stage2": {
        "lenses": {
          "trend": {
            "score": 5,
            "direction": "BEAR",
            "analysis": "The Nasdaq is in a bearish trend with mixed SMA alignment and price at the 50-week SMA, indicating a neutral and unclear trend structure. The RSI is approaching oversold, suggesting a potential bounce up.",
            "key_level": 21647.61
          },
          "reversal": {
            "score": 8,
            "direction": "NEUTRAL",
            "analysis": "The Nasdaq is approaching oversold levels with an RSI of 33.6, but the price is still below the lower Bollinger Band. The weekly SMA50 is also at the current price level, which could act as a support, but the lack of clear trend and mixed SMA alignment suggest caution.",
            "key_level": 21647.61
          },
          "momentum": {
            "score": 5,
            "direction": "BEAR",
            "analysis": "The MACD histogram is negative, and the RSI is approaching oversold levels, suggesting bearish momentum. The volume trend is slightly above average, similar to the S&P 500, which might indicate a more substantial move if the trend reverses.",
            "key_level": 21647.61
          },
          "volatility": {
            "score": 5,
            "direction": "BEAR",
            "analysis": "The Bollinger Band width is relatively low at 6.4%, and the ATR ratio is contracting, indicating decreased volatility, but the price is already below the lower band, suggesting a potential continuation of the downtrend. The VIX correlation is aligned with the bearish market regime.",
            "key_level": 24004.13
          },
          "risk_reward": {
            "score": 4,
            "direction": "BEAR",
            "analysis": "The Nasdaq has a downside risk of 2,815.70 and an upside potential of 356.49, resulting in a 1:7.9 R:R ratio, which is not particularly favorable for a new bearish position.",
            "key_level": 21647.61
          }
        },
        "composite_score": 5.4,
        "consensus_direction": "BEAR",
        "confidence": 0.54
      },
      "stage5": {
        "A": null,
        "B": null,
        "C": null,
        "D": null
      },
      "stage6": null,
      "stage7": {
        "hallucinations_found": [],
        "logical_errors": [
          "The AI's bearish direction contradicts the low RSI value of 33.6, which typically indicates an oversold condition and potential for a bullish reversal."
        ],
        "missing_risks": [
          "The analysis does not consider the potential impact of the price being below the lower Bollinger Band, which could lead to a sharp rebound."
        ],
        "overconfidence": true,
        "adjusted_confidence": 0.4,
        "validation_passed": false,
        "final_verdict": "REDUCE_CONFIDENCE",
        "auditor_notes": "The analysis lacks concrete evidence to support the bearish direction, and the low RSI value suggests a potential reversal. The AI's confidence is not justified by the data spread. Further analysis is needed to consider the potential risks and opportunities."
      },
      "synthesis": {
        "verdict": "NO_TRADE",
        "final_confidence": 0.4,
        "chain_of_thought": "Analysen av Nasdaq visar en bearish trend med en kompositbetyg på 5,4/10, men den låga RSI-värdet på 33,6 tyder på en potentiell vändning. Dessutom saknar analysen konkreta bevis för att stödja den beariska riktningen, vilket gör att AI:s konfidens inte är berättigad av datamaterialet. Korsvalideringen visar att analysen brister i bevis och att den låga RSI-värdet kan tyda på en vändning, vilket gör att jag måste reducera konfidensen till 40%. Med tanke på att konfidensen är under 0,55 och att det saknas starka skäl för att åsidosätta korsvalideringens resultat, är det bästa beslutet att inte genomföra någon handel.",
        "entry_price": 0.0,
        "stop_loss": 0.0,
        "take_profit": 0.0,
        "risk_reward": "1:0,13",
        "key_catalyst": "Den låga RSI-värdet på 33,6 tyder på en potentiell vändning.",
        "biggest_risk": "Den beariska trenden kan fortsätta och orsaka förluster.",
        "time_horizon": "1-3 dagar",
        "exit_strategy": "Om en position skulle öppnas, skulle jag stänga den om priset når take-profit-nivån eller om stop-loss-nivån nås. Dessutom skulle jag kontinuerligt övervaka marknaden och justera strategin om förhållandena förändras. I det här fallet, då beslutet är att inte handla, är det viktigt att fortsätta övervaka marknaden och vänta på tydligare signaler innan någon handel genomförs."
      },
      "headlines": [
        {
          "headline": "Nasdaq Price Forecasts Today: Expert Analysis & Predictions",
          "source": "www.fxempire.com",
          "datetime": "2026-03-23",
          "url": "https://www.fxempire.com/forecasts/tech100-usd",
          "summary": "NASDAQ Index, SP500, Dow Jones Forecasts – Stocks Dive As Traders Worry That U.S. Plans A Ground Operation In Iran · US30-USD-0.64%TECH100-USD-0.88%."
        },
        {
          "headline": "Nasdaq: Stock Market, Data Updates, Reports & News",
          "source": "www.nasdaq.com",
          "datetime": "2026-03-23",
          "url": "https://www.nasdaq.com/",
          "summary": "Get the latest stock market news, stock information & quotes, data analysis reports, as well as a general overview of the market landscape from Nasdaq."
        },
        {
          "headline": "US Tech 100 - Nasdaq Index Overview - IG Group",
          "source": "www.ig.com",
          "datetime": "2026-03-23",
          "url": "https://www.ig.com/en/indices/markets-indices/us-tech-100",
          "summary": "See market data and sentiment and spot trading opportunities for IG's US Tech 100 stock index - settled on the price of the NASDAQ."
        },
        {
          "headline": "NASDAQ-100 Technology Sector Index (NDXT)",
          "source": "www.nasdaq.com",
          "datetime": "2026-03-23",
          "url": "https://www.nasdaq.com/market-activity/index/ndxt",
          "summary": "Find the latest information on NASDAQ-100 Technology Sector Index (NDXT), including data, charts, related news, and more from Nasdaq.com."
        },
        {
          "headline": "NASDAQ 100 INDEX TODAY | NDX LIVE TICKER",
          "source": "markets.businessinsider.com",
          "datetime": "2026-03-23",
          "url": "https://markets.businessinsider.com/index/nasdaq_100",
          "summary": "NASDAQ 100 Key Figures ; Performance, -3.63 %, -6.14 % ; High, 25,343.97, 26,165.08 ; Low, 23,759.97, 23,759.97 ; Volatility, 17.94, 15.64"
        },
        {
          "headline": "Technology Stock Performance",
          "source": "finance.yahoo.com",
          "datetime": "2026-03-23",
          "url": "https://finance.yahoo.com/sectors/technology/",
          "summary": "Yahoo Finance's Technology performance dashboard help you quickly analyze & examine stock performance across the Technology sector using dozens of metrics"
        },
        {
          "headline": "Market Activity",
          "source": "www.nasdaq.com",
          "datetime": "2026-03-23",
          "url": "https://www.nasdaq.com/market-activity",
          "summary": "Current trading halts and suspensions are listed in the Market Activity section on the Summary page for the stock, in the Notifications area of the page."
        },
        {
          "headline": "U.S. Stock Market Headlines | Breaking Stock Market News",
          "source": "www.reuters.com",
          "datetime": "2026-03-23",
          "url": "https://www.reuters.com/markets/us/",
          "summary": "Markets Now March 20, 2026 · 3:33 PM PDT. US stocks end sharply lower; Middle East turmoil fans inflation fear. Wall Street ended sharply lower on Friday,"
        },
        {
          "headline": "MarketWatch: Stock Market News - Financial News ...",
          "source": "www.marketwatch.com",
          "datetime": "2026-03-23",
          "url": "https://www.marketwatch.com/?gaa_at=eafs&gaa_n=AWEtsqdkulnEKzSB8byIDCHlxLlx5gM4Slcoxp27NpsGMT83QBQwXTt1pg3B&gaa_ts=69c0ed8f&gaa_sig=TsCJonkyXU8QLyvghNRrK8ZZOtfdQ6X_S4L7aorItMDNmnCXDRgiEsNExdccDaJJbf_EPoq31lSqVJ1mN6qiyg%3D%3D",
          "summary": "MarketWatch provides the latest stock market, financial and business news. Get stock market quotes, personal finance advice, company news and more."
        },
        {
          "headline": "US 100 Tech Index - Index Price | Live Quote",
          "source": "tradingeconomics.com",
          "datetime": "2026-03-23",
          "url": "https://tradingeconomics.com/us100:ind",
          "summary": "Looking ahead, we forecast US 100 Tech Index to be priced at 23181 by the end of this quarter and at 21157 in one year, according to Trading Economics global"
        }
      ],
      "final_verdict": "NO_TRADE",
      "final_confidence": 0.4,
      "trading_plan": null
    },
    {
      "asset": {
        "ticker": "^GSPC",
        "display_name": "S&P 500",
        "news_keywords": [
          "S&P 500",
          "US economy",
          "Wall Street"
        ],
        "asset_type": "index",
        "category": "Index"
      },
      "tech": {
        "current_price": 6506.48,
        "rsi_value": 29.88,
        "sma_20": 6770.57,
        "sma_50": 6857.76,
        "sma_200": 6621.73,
        "sma_50w": 6458.16,
        "atr_value": 104.52,
        "price_vs_sma": "below",
        "price_vs_weekly_sma": "at",
        "sma_alignment": "mixed",
        "sma_bias": "bearish",
        "rsi_trend_2d": -6.09,
        "atr_ratio": 1.13,
        "volume_ratio": 1.21,
        "vix_value": 26.78,
        "vix_level": "elevated",
        "near_resistance": false,
        "near_support": false,
        "supports": [
          5773.31,
          5119.26,
          4953.56
        ],
        "resistances": [
          6961.31
        ],
        "macd_value": -77.2362,
        "macd_signal": -52.7605,
        "macd_histogram": -24.4757,
        "macd_cross": "none",
        "bb_upper": 7006.67,
        "bb_lower": 6534.47,
        "bb_middle": 6770.57,
        "bb_position": "below_lower",
        "bb_width": 7.26
      },
      "stage2": {
        "lenses": {
          "trend": {
            "score": 4,
            "direction": "BEAR",
            "analysis": "The S&P 500 is in a bearish trend with mixed SMA alignment and price at the 50-week SMA, indicating a neutral and unclear trend structure. The RSI is oversold, suggesting a potential bounce up.",
            "key_level": 6506.48
          },
          "reversal": {
            "score": 6,
            "direction": "BULL",
            "analysis": "The S&P 500 is showing signs of reversal safety with an oversold RSI of 29.9 and a potential bounce up, and the price is near the lower Bollinger Band. The weekly SMA50 is also at the current price level, which could act as a support.",
            "key_level": 6506.48
          },
          "momentum": {
            "score": 4,
            "direction": "BEAR",
            "analysis": "The MACD histogram is negative and the RSI is oversold, indicating bearish momentum with a potential for a bounce. The volume trend is slightly above average, which could suggest a more significant move if momentum shifts.",
            "key_level": 6506.48
          },
          "volatility": {
            "score": 4,
            "direction": "BEAR",
            "analysis": "The Bollinger Band width is relatively low at 7.3%, and the ATR ratio is contracting, indicating decreased volatility, but the price is already below the lower band, suggesting a potential continuation of the downtrend. The VIX correlation is aligned with the bearish market regime.",
            "key_level": 6931.31
          },
          "risk_reward": {
            "score": 7,
            "direction": "BEAR",
            "analysis": "The S&P 500 has a downside risk of 733.17 and an upside potential of 454.83, resulting in a 1:1.6 R:R ratio, which is somewhat favorable for a bearish position given the oversold RSI and potential bounce.",
            "key_level": 6506.48
          }
        },
        "composite_score": 5.0,
        "consensus_direction": "BEAR",
        "confidence": 0.5
      },
      "stage5": {
        "A": null,
        "B": null,
        "C": null,
        "D": null
      },
      "stage6": null,
      "stage7": {
        "hallucinations_found": [],
        "logical_errors": [
          "The AI's bearish direction contradicts the low RSI value of 29.9, which typically indicates an oversold condition and potential for a bullish reversal."
        ],
        "missing_risks": [
          "The analysis does not consider the potential impact of the price being below the lower Bollinger Band, which could lead to a sharp rebound."
        ],
        "overconfidence": true,
        "adjusted_confidence": 0.4,
        "validation_passed": false,
        "final_verdict": "REDUCE_CONFIDENCE",
        "auditor_notes": "The analysis lacks concrete evidence to support the bearish direction, and the absence of historical analogs, inter-market, and fundamental verdicts raises concerns about the thoroughness of the analysis. The low RSI value and price being below the lower Bollinger Band suggest potential for a bullish reversal, which contradicts the bearish direction. Further analysis is needed to justify the confidence level."
      },
      "synthesis": {
        "verdict": "NO_TRADE",
        "final_confidence": 0.4,
        "chain_of_thought": "Analysen av S&P 500 visar en bearish trend med en kompositbetyg på 5.0/10. Trenden är bearish med en SMA-alignment som är blandad och priset är vid 50-w. Reversal-signalen är positiv med en oversold RSI på 29.9, men momentum-indikatorn MACD är negativ. Volatiliteten är relativt låg med en Bollinger Band-bredd på 7.3% och en ATR-ratio som är kontrakt. Risk-reward-förhållandet är 1:0.62, vilket tyder på en högre nedåtrisk på 733.17 jämfört med uppsidan på 454.83. Djupforskningen saknar historiska analogier, intermarknadsanalys och fundamentala faktorer, vilket gör det svårt att dra några tydliga slutsatser. Djävulens advokat har inga invändningar, men korsvalideringen reducerar konfidensen till 40% på grund av bristen på konkret bevis för den beariska riktningen. Med en konfidens under 0.55 är det bäst att inte genomföra någon handel.",
        "entry_price": 0.0,
        "stop_loss": 0.0,
        "take_profit": 0.0,
        "risk_reward": "1:0.62",
        "key_catalyst": "Bristen på konkret bevis för den beariska riktningen är den största katalysatorn för att inte genomföra någon handel.",
        "biggest_risk": "Den största risken är att marknaden fortsätter att falla och att nedåtrisken på 733.17 realiseras.",
        "time_horizon": "1-3 dagar",
        "exit_strategy": "Om en handel skulle genomföras, skulle exit-strategin vara att stänga positionen om priset når stop-loss-nivån eller om risk-reward-förhållandet förändras. Det är också viktigt att kontinuerligt övervaka marknaden och justera strategin om nya information blir tillgänglig. I det här fallet är det dock bäst att inte genomföra någon handel på grund av den låga konfidensen."
      },
      "headlines": [
        {
          "headline": "S&P 500 (^GSPC) Charts, Data & News - Yahoo Finance",
          "source": "finance.yahoo.com",
          "datetime": "2026-03-23",
          "url": "https://finance.yahoo.com/quote/%5EGSPC/",
          "summary": "Stock market today: Dow, S&P 500, Nasdaq futures fall as 4-week down spiral ... US stock futures fall after Trump issues 48-hr deadline on Iran."
        },
        {
          "headline": "S&P 500 INDEX TODAY | INX LIVE TICKER - Markets Insider",
          "source": "markets.businessinsider.com",
          "datetime": "2026-03-23",
          "url": "https://markets.businessinsider.com/index/s&p_500",
          "summary": "S&P 500 Today: Get all information on the S&P 500 Index including historical chart, news and constituents."
        },
        {
          "headline": "S&P 500 Index (SPX) - Investing.com",
          "source": "www.investing.com",
          "datetime": "2026-03-23",
          "url": "https://www.investing.com/indices/us-spx-500",
          "summary": "Today, the S&P 500 opened at 6,594.66. What is the trading volume for S&P 500? The current volume for S&P 500 is 0."
        },
        {
          "headline": "United States Stock Market Index - Quote - Chart - Historical Data",
          "source": "tradingeconomics.com",
          "datetime": "2026-03-23",
          "url": "https://tradingeconomics.com/united-states/stock-market",
          "summary": "The S&P 500 dropped 1.5%, the Nasdaq 100 plunged 1.8% to six-month lows while the Dow Jones lost 0.8% to four-month lows on Friday amid escalating Middle East"
        },
        {
          "headline": "U.S. Stock Market Headlines | Breaking Stock Market News - Reuters",
          "source": "www.reuters.com",
          "datetime": "2026-03-23",
          "url": "https://www.reuters.com/markets/us/",
          "summary": "Wall Street ended sharply lower on Friday, with losses in heavyweights Nvidia and Microsoft, as the U.S.-Israeli war against Iran entered its fourth week,"
        },
        {
          "headline": "S&P 500 Index Overview - SPX - MarketWatch",
          "source": "www.marketwatch.com",
          "datetime": "2026-03-23",
          "url": "https://www.marketwatch.com/investing/index/spx?gaa_at=eafs&gaa_n=AWEtsqeMTXy-Ug8C_3-upUFf0yJh1ANX0HzLq-de_2zzHSx47KWwbvZ8gjrm&gaa_ts=69c0ee92&gaa_sig=9AnQiNxRK1_Ej4k3FnexyhfwGJ83htp1SHprWOvLgkWNgfIQyrMIJuGoj1rzAa1_2l65hfq9k8efWPQ9QIjyCQ%3D%3D",
          "summary": "SPX | A complete S&P 500 Index index overview by MarketWatch. View stock market news, stock market data and trading information."
        },
        {
          "headline": "SPX: S&P 500 Index - Stock Price, Quote and News - CNBC",
          "source": "www.cnbc.com",
          "datetime": "2026-03-23",
          "url": "https://www.cnbc.com/quotes/.SPX",
          "summary": "S&P 500 Index .SPX:INDEX · Open6,594.66 · Day High6,594.66 · Day Low6,473.52 · Prev Close6,506.48 · 52 Week High7,002.28 · 52 Week High Date01/28/26 · 52 Week Low"
        },
        {
          "headline": "Weekly Trader's Stock Market Outlook | Charles Schwab",
          "source": "www.schwab.com",
          "datetime": "2026-03-23",
          "url": "https://www.schwab.com/learn/story/weekly-traders-outlook",
          "summary": "Read our weekly market review, complete with commentary on the previous week in the stock markets and our outlook for the upcoming week."
        },
        {
          "headline": "Daily market snapshot - Edward Jones",
          "source": "www.edwardjones.com",
          "datetime": "2026-03-23",
          "url": "https://www.edwardjones.com/us-en/market-news-insights/stock-market-news/daily-market-recap",
          "summary": "Stocks close lower amid geopolitical uncertainty and higher bond yields – U.S. equity markets closed sharply lower on Friday, weighed down"
        },
        {
          "headline": "Stock Market Data - US Markets, World Markets, and Stock Quotes",
          "source": "www.cnn.com",
          "datetime": "2026-03-23",
          "url": "https://www.cnn.com/markets",
          "summary": "Up-to-date stock market data coverage from CNN. Get the latest updates on US markets, world markets, stock quotes, crypto, commodities and currencies."
        }
      ],
      "final_verdict": "NO_TRADE",
      "final_confidence": 0.4,
      "trading_plan": null
    }
  ],
  "final_picks": [],
  "yesterday_review": null,
  "log": [
    "**Unitron 8-Stegs Djupanalys** — 17 tillgångar, 07:21",
    "",
    "### Steg 0: Datafundament",
    "Hämtar marknadsdata och makroindikatorer...",
    "VIX: 26.8",
    "DXY: 99.77",
    "US 10Y: 4.39%",
    "Data: DAX 40 (1/17)",
    "Data: OMXS30 (2/17)",
    "Data: S&P 500 (3/17)",
    "Data: Nasdaq (4/17)",
    "Data: FTSE 100 (5/17)",
    "Data: Nikkei 225 (6/17)",
    "Data: Hang Seng (7/17)",
    "Data: Guld (8/17)",
    "Data: Silver (9/17)",
    "Data: Olja (WTI) (10/17)",
    "Data: Naturgas (11/17)",
    "Data: Platina (12/17)",
    "Data: Koppar (13/17)",
    "Data: Bitcoin (14/17)",
    "Data: Ethereum (15/17)",
    "Data: Solana (16/17)",
    "Data: XRP (17/17)",
    "Steg 0 klart: 17/17 tillgångar redo",
    "",
    "### Steg 8: Gårdagens Utvärdering",
    "Inga gårdagsresultat tillgängliga — hoppar över",
    "",
    "### Steg 1: Global Makroankare (Gemini)",
    "Analyserar marknadsregim (Gemini)...",
    "Marknadsregim: RISK_OFF",
    "The VIX is elevated above 25, indicating heightened market fear and uncertainty. The US Dollar Index is at a relatively ",
    "",
    "### Steg 2: Flerlins Teknisk Skanning (Groq)",
    "Lins: TREND (17 tillgångar)",
    "Lins: REVERSAL (17 tillgångar)",
    "Lins: MOMENTUM (17 tillgångar)",
    "Lins: VOLATILITY (17 tillgångar)",
    "Lins: RISK_REWARD (17 tillgångar)",
    "[~] DAX 40: 4.0/10 BEAR",
    "[~] OMXS30: 4.2/10 BEAR",
    "[~] S&P 500: 5.0/10 BEAR",
    "[~] Nasdaq: 5.4/10 BEAR",
    "[~] FTSE 100: 4.0/10 BEAR",
    "[~] Nikkei 225: 4.6/10 BEAR",
    "[-] Hang Seng: 2.8/10 BEAR",
    "[~] Guld: 4.8/10 BULL",
    "[-] Silver: 3.3/10 NEUTRAL",
    "[+] Olja (WTI): 8.0/10 NEUTRAL",
    "[~] Naturgas: 4.0/10 NEUTRAL",
    "[-] Platina: 3.3/10 NEUTRAL",
    "[~] Koppar: 4.8/10 BEAR",
    "[~] Bitcoin: 4.0/10 BEAR",
    "[~] Ethereum: 4.4/10 BEAR",
    "[~] Solana: 4.0/10 BEAR",
    "[~] XRP: 4.0/10 BEAR",
    "",
    "### Steg 3-4: Ranking & Premium-Nyheter",
    "Olja (WTI): 8.0/10 NEUTRAL",
    "Nasdaq: 5.4/10 BEAR",
    "S&P 500: 5.0/10 BEAR",
    "Guld: 4.8/10 BULL",
    "Koppar: 4.8/10 BEAR",
    "Nikkei 225: 4.6/10 BEAR",
    "Ethereum: 4.4/10 BEAR",
    "OMXS30: 4.2/10 BEAR",
    "DAX 40: 4.0/10 BEAR",
    "FTSE 100: 4.0/10 BEAR",
    "Naturgas: 4.0/10 NEUTRAL",
    "Bitcoin: 4.0/10 BEAR",
    "Solana: 4.0/10 BEAR",
    "XRP: 4.0/10 BEAR",
    "Silver: 3.3/10 NEUTRAL",
    "Platina: 3.3/10 NEUTRAL",
    "Hang Seng: 2.8/10 BEAR",
    "Topp 3 vidare till djupanalys",
    "Hämtar premium-nyheter (Tavily) för 3 finalister...",
    "Olja (WTI): 10 artiklar",
    "Nasdaq: 10 artiklar",
    "S&P 500: 10 artiklar",
    "**3 finalister vidare till djupanalys**",
    "",
    "### Steg 5: Högdimensionell Djupanalys (Gemini)",
    "Modul A: Historiska Analogier — Olja (WTI)",
    "  Historisk dom: BEARISH",
    "Modul B: Intermarknadsanalys — Olja (WTI)",
    "  Intermarknadsdom: DIVERGENT",
    "Modul C: Utbud/Efterfrågan & Geopolitik — Olja (WTI)",
    "  Fundamental dom: BEARISH",
    "Modul D: Scenariostresstest — Olja (WTI)",
    "  Modul D misslyckades",
    "Modul A: Historiska Analogier — Nasdaq",
    "  Modul A misslyckades",
    "Modul B: Intermarknadsanalys — Nasdaq",
    "  Modul B misslyckades",
    "Modul C: Utbud/Efterfrågan & Geopolitik — Nasdaq",
    "  Modul C misslyckades",
    "Modul D: Scenariostresstest — Nasdaq",
    "  Modul D misslyckades",
    "Modul A: Historiska Analogier — S&P 500",
    "  Modul A misslyckades",
    "Modul B: Intermarknadsanalys — S&P 500",
    "  Modul B misslyckades",
    "Modul C: Utbud/Efterfrågan & Geopolitik — S&P 500",
    "  Modul C misslyckades",
    "Modul D: Scenariostresstest — S&P 500",
    "  Modul D misslyckades",
    "",
    "### Steg 6: Djävulens Advokat (Gemini)",
    "Djävulens Advokat: Olja (WTI)",
    "Olja (WTI): Devil's Advocate misslyckades",
    "Djävulens Advokat: Nasdaq",
    "Nasdaq: Devil's Advocate misslyckades",
    "Djävulens Advokat: S&P 500",
    "S&P 500: Devil's Advocate misslyckades",
    "",
    "### Steg 7: Korsvalidering (Groq)",
    "Korsvalidering: Olja (WTI)",
    "[~] Olja (WTI): REDUCE_CONFIDENCE (justerad konfidens: 60%)",
    "Korsvalidering: Nasdaq",
    "[~] Nasdaq: REDUCE_CONFIDENCE (justerad konfidens: 40%)",
    "Korsvalidering: S&P 500",
    "[~] S&P 500: REDUCE_CONFIDENCE (justerad konfidens: 40%)",
    "",
    "### Slutgiltig Syntes & Handelsplan",
    "Slutgiltig syntes: Olja (WTI)",
    "[-] Olja (WTI): NO_TRADE (40%)",
    "Slutgiltig syntes: Nasdaq",
    "[-] Nasdaq: NO_TRADE (40%)",
    "Slutgiltig syntes: S&P 500",
    "[-] S&P 500: NO_TRADE (40%)",
    "",
    "**Analys klar!** 0 handelsrekommendationer"
  ],
  "total_assets": 17,
  "stage_calls": {
    "stage0": 17,
    "stage1": 1,
    "stage2_batches": 25,
    "stage5": 12,
    "stage6": 3,
    "stage7": 3,
    "synthesis": 3,
    "stage8": 0
  }
}